gmssl.py
gmssl_python-2.2.2.dist-info/LICENSE
gmssl_python-2.2.2.dist-info/METADATA
gmssl_python-2.2.2.dist-info/WHEEL
gmssl_python-2.2.2.dist-info/top_level.txt
gmssl_python-2.2.2.dist-info/RECORD
