Metadata-Version: 2.1
Name: gmssl-python
Version: 2.2.2
Summary: Python binding of the GmSSL library with ctypes
Author-email: Zhi Guan <guan@pku.edu.cn>
Project-URL: Homepage, https://gmssl.github.io/GmSSL-Python/
Project-URL: Bug Tracker, https://github.com/GmSSL/GmSSL-Python/issues
Classifier: Programming Language :: Python :: 3
Classifier: License :: OSI Approved :: Apache Software License
Classifier: Operating System :: OS Independent
Requires-Python: >=3.7
License-File: LICENSE
